codev/__init__.py
codev/bin/codev
codev/bin/codev-perform
codev/control/__init__.py
codev/control/cli.py
codev/control/isolation.py
codev/control/log.py
codev/core/__init__.py
codev/core/cli.py
codev/core/debug.py
codev/core/infrastructure.py
codev/core/isolator.py
codev/core/log.py
codev/core/machines.py
codev/core/performer.py
codev/core/provider.py
codev/core/settings.py
codev/core/source.py
codev/core/utils.py
codev/core/providers/__init__.py
codev/core/providers/isolators/__init__.py
codev/core/providers/isolators/directory.py
codev/core/providers/isolators/lxc.py
codev/core/providers/isolators/lxd.py
codev/core/providers/isolators/none.py
codev/core/providers/isolators/virtualenv.py
codev/core/providers/machines/__init__.py
codev/core/providers/machines/real.py
codev/core/providers/machines/virtualbox.py
codev/core/providers/machines/lxc/__init__.py
codev/core/providers/machines/lxc/scripts/clsync-synchandler-rsyncshell.sh
codev/core/providers/machines/lxc/templates/default/config
codev/core/providers/machines/lxc/templates/static/config
codev/core/providers/machines/lxc/templates/static/network_interfaces
codev/core/providers/machines/lxc/templates/toplevel/config
codev/core/providers/machines/lxd/__init__.py
codev/core/providers/machines/lxd/scripts/clsync-synchandler-rsyncshell.sh
codev/core/providers/machines/lxd/templates/default/config
codev/core/providers/machines/lxd/templates/static/config
codev/core/providers/machines/lxd/templates/static/network_interfaces
codev/core/providers/machines/lxd/templates/toplevel/config
codev/core/providers/machines/ubuntu_template/ks.cfg
codev/core/providers/machines/ubuntu_template/isolinux/isolinux.cfg
codev/core/providers/machines/ubuntu_template/isolinux/langlist
codev/core/providers/machines/ubuntu_template/isolinux/txt.cfg
codev/core/providers/performers/__init__.py
codev/core/providers/performers/local.py
codev/core/providers/performers/ssh.py
codev-0.7.4a3.dist-info/DESCRIPTION.rst
codev-0.7.4a3.dist-info/METADATA
codev-0.7.4a3.dist-info/RECORD
codev-0.7.4a3.dist-info/WHEEL
codev-0.7.4a3.dist-info/metadata.json
codev-0.7.4a3.dist-info/top_level.txt
