Metadata-Version: 2.0
Name: codev
Version: 0.7.4a3
Summary: Continuous delivery tool
Home-page: http://www.baseclue.com/codev/
Author: Jan Češpivo (http://www.baseclue.com/)
Author-email: jan.cespivo@gmail.com
License: Apache 2.0
Platform: UNKNOWN
Classifier: Development Status :: 4 - Beta
Classifier: Environment :: Console
Classifier: Intended Audience :: Developers
Classifier: License :: OSI Approved :: Apache Software License
Classifier: Operating System :: POSIX :: Linux
Classifier: Programming Language :: Python
Classifier: Programming Language :: Python :: 3
Requires-Dist: click (==6.6)
Requires-Dist: PyYAML (==3.11)
Requires-Dist: paramiko (==2.0.0)
Requires-Dist: colorama (==0.3.7)
Requires-Dist: GitPython (==2.0.2)
